README.md
setup.py
grainger_product_scraper/__init__.py
grainger_product_scraper.egg-info/PKG-INFO
grainger_product_scraper.egg-info/SOURCES.txt
grainger_product_scraper.egg-info/dependency_links.txt
grainger_product_scraper.egg-info/requires.txt
grainger_product_scraper.egg-info/top_level.txt