Metadata-Version: 2.1
Name: grainger-product-scraper
Version: 1.0.0
Summary: A python library to scrape product data on grainger automatically.
Home-page: https://datakund.com
Author: DataKund
Author-email: datakund@gmail.com
License: Apache License 2.0
Keywords: grainger python bot_studio scraper data product info web-scraping
Platform: UNKNOWN
